Metadata-Version: 1.0
Name: tegro-parser
Version: 1.1
Summary: TegroParser - module for working with tegro.money API
Home-page: UNKNOWN
Author: UNKNOWN
Author-email: UNKNOWN
License: UNKNOWN
Platform: UNKNOWN
